Workbook

Sheet Questions
A1: Question | B1: Le Tip ! | C1: Thème | D1: Sujet | F1: Remarques de Boubou
A2: Quelle est la première pensée que tu as au réveil la majorité des matins ? | C2: QUOTIDIEN | D2: Matin | E2: =COUNTIF(Questions!D:D,D2) -> 2
A3: Si tu pouvais changer une chose dans ta routine matinale actuelle, ce serait quoi ? | C3: QUOTIDIEN | D3: Matin | E3: =COUNTIF(Questions!D:D,D3) -> 2
A4: Quelle est la personne la plus intelligente du groupe ? | C4: ENTRE NOUS | D4: Meilleurs | E4: =COUNTIF(Questions!D:D,D4) -> 2
A5: Qui est la personne la plus drôle du groupe ? | C5: ENTRE NOUS | D5: Meilleurs | E5: =COUNTIF(Questions!D:D,D5) -> 2
A6: Y a-t-il un moment de ta vie dont tu n'as aucun souvenir mais qu'on t'a souvent raconté ? | C6: RETOUR EN ARRIERE | D6: Moments de vie | E6: =COUNTIF(Questions!D:D,D6) -> 2
A7: Quel moment de vie prenais-tu pour acquis et ne te satisfait pas, avant de te rendre compte qu'il était vraiment unique ? | C7: RETOUR EN ARRIERE | D7: Moments de vie | E7: =COUNTIF(Questions!D:D,D7) -> 2 | F7: 23
A8: Quelle qualité partages tu avec ton voisin de gauche ? | C8: ENTRE NOUS | D8: Partage | E8: =COUNTIF(Questions!D:D,D8) -> 2
A9: Si tu devais offrir un cadeau à ton voisin de gauche, que lui donnerais-tu ? | C9: ENTRE NOUS | D9: Partage | E9: =COUNTIF(Questions!D:D,D9) -> 2
A10: Quel est ton sens le plus développé ? | C10: QUOTIDIEN | D10: 5 sens | E10: =COUNTIF(Questions!D:D,D10) -> 2
A11: Si tu perdais un sens pour toujours, lequel choisis-tu de sacrifier ? | C11: QUOTIDIEN | D11: 5 sens | E11: =COUNTIF(Questions!D:D,D11) -> 2
A12: Quel est le mot qui résume toute ta période scolaire ? | C12: RETOUR EN ARRIERE | D12: A l'école | E12: =COUNTIF(Questions!D:D,D12) -> 2
A13: Quelle était ta matière préférée à l'école ? | C13: RETOUR EN ARRIERE | D13: A l'école | E13: =COUNTIF(Questions!D:D,D13) -> 2
A14: Si tu gagnais à la loterie, quel serait ton premier achat ? | C14: AMBITIONS | D14: Achats | E14: =COUNTIF(Questions!D:D,D14) -> 2
A15: Quelle est la chose la plus chère que tu possèdes en terme de prix ? | C15: AMBITIONS | D15: Achats | E15: =COUNTIF(Questions!D:D,D15) -> 2
A16: Quelle est l’activité manuelle que tu essayes d'apprendre actuellement ? | C16: PASSIONS & ACTIVITES | D16: Activité | E16: =COUNTIF(Questions!D:D,D16) -> 2
A17: Quelle est l'activité qui te détend totalement ? | C17: PASSIONS & ACTIVITES | D17: Activité | E17: =COUNTIF(Questions!D:D,D17) -> 2
A18: Quelle est la célébrité que tu trouves le plus BG ? | C18: CINE & MUSIQUE | D18: Admirateur | E18: =COUNTIF(Questions!D:D,D18) -> 2
A19: Si tu pouvais être n’importe quelle célébrité pendant une journée, qui serais-tu ? | C19: CINE & MUSIQUE | D19: Admirateur | E19: =COUNTIF(Questions!D:D,D19) -> 2
... A32: Quel est le film d’animation qui te rappelle ton enfance ? | C32: CINE & MUSIQUE | D32: Animation | E32: =COUNTIF(Questions!D:D,D32) -> 2
A33: Quel est le film d'animation le plus célèbre, que tu n'as-tu jamais vu ? | C33: CINE & MUSIQUE | D33: Animation | E33: =COUNTIF(Questions!D:D,D33) -> 2 | F33: 23
A34: Comment tu aimes fêter ton anniversaire ? | C34: QUOTIDIEN | D34: Anniversaire | E34: =COUNTIF(Questions!D:D,D34) -> 2
A35: Si tu pouvais choisir ton cadeau d'anniversaire parfait cette année, ce serait quoi ? | C35: QUOTIDIEN | D35: Anniversaire | E35: =COUNTIF(Questions!D:D,D35) -> 2
A36: Qui du groupe a l'air le plus sérieux mais est en réalité le plus fou ? | C36: ENTRE NOUS | D36: Apparences trompeuses | E36: =COUNTIF(Questions!D:D,D36) -> 2
A37: Qui du groupe a l'air le plus intelligent, mais est en vrai le plus con ? | C37: ENTRE NOUS | D37: Apparences trompeuses | E37: =COUNTIF(Questions!D:D,D37) -> 2
A38: Si tu pouvais concevoir ta maison idéale, comment elle serait ? | C38: PASSIONS & ACTIVITES | D38: Architecture | E38: =COUNTIF(Questions!D:D,D38) -> 2
A39: Quel est le bâtiment ou lieu que tu trouves le plus beau dans le monde ? | C39: PASSIONS & ACTIVITES | D39: Architecture | E39: =COUNTIF(Questions!D:D,D39) -> 2
A40: Si tu pouvais maîtriser parfaitement une forme d'art, laquelle choisirais-tu ? | C40: PASSIONS & ACTIVITES | D40: Art | E40: =COUNTIF(Questions!D:D,D40) -> 2
A41: Quelle œuvre d'art (tableau, sculpture, photo...) t'a un jour laissé sans voix ? | C41: PASSIONS & ACTIVITES | D41: Art | E41: =COUNTIF(Questions!D:D,D41) -> 2
A42: Quelle est la vision de toi-même dans 10 ans que tu portes mais n'avoues à presque personne ? | C42: AMBITIONS | D42: Aspirations profondes | E42: =COUNTIF(Questions!D:D,D42) -> 2
A43: Si l'argent et le regard des autres n'existaient pas, comment passerais-tu tes journées ? | C43: AMBITIONS | D43: Aspirations profondes | E43: =COUNTIF(Questions!D:D,D43) -> 2
A44: Quel est ton signe astrologique et est-ce que tu y crois ? Exemple de réponse : Scorpion/Oui | C44: QUI ES-TU ? | D44: Astrologie | E44: =COUNTIF(Questions!D:D,D44) -> 2
A45: Quelle est la superstitition à laquelle tu crois ? | C45: QUI ES-TU ? | D45: Astrologie | E45: =COUNTIF(Questions!D:D,D45) -> 2
... A50: Quel serait le titre de ton autobiographie ? | C50: RETOUR EN ARRIERE | D50: Autobiographie | E50: =COUNTIF(Questions!D:D,D50) -> 2
A51: C'est le moment d'écrire un livre sur la vie de quelqu'un, sur qui tu l'écris ? | C51: RETOUR EN ARRIERE | D51: Autobiographie | E51: =COUNTIF(Questions!D:D,D51) -> 2 | F51: 23
A52: Quel aspect ou défi de la vie future te fait le plus peur ? | C52: AMBITIONS | D52: Avenir | E52: =COUNTIF(Questions!D:D,D52) -> 2
A53: Quels sont les trois mots qui te viennent à l'esprit quand tu penses à l'avenir ? | C53: AMBITIONS | D53: Avenir | E53: =COUNTIF(Questions!D:D,D53) -> 2
A54: Quelle est la théorie du complot à laquelle tu adhères secrètement ? | C54: LES DOSSIERS | D54: Aveux | E54: =COUNTIF(Questions!D:D,D54) -> 2
A55: Quelle opinion impopulaire assumes-tu complètement ? | C55: LES DOSSIERS | D55: Aveux | E55: =COUNTIF(Questions!D:D,D55) -> 2
A56: Quel type d'humour te fait vraiment rire ? | C56: LES DOSSIERS | D56: Blague | E56: =COUNTIF(Questions!D:D,D56) -> 2
A57: Raconte-nous ta meilleure blague ? | C57: LES DOSSIERS | D57: Blague | E57: =COUNTIF(Questions!D:D,D57) -> 2
A58: Avec combien de personnes différentes as-tu couché ? | C58: HOT | D58: Bodycount | E58: =COUNTIF(Questions!D:D,D58) -> 2
A59: A quel âge as-tu eu ta première relation ? | C59: HOT | D59: Bodycount | E59: =COUNTIF(Questions!D:D,D59) -> 2
A60: Quelle est la boisson la plus originale ou étrange que tu aies goûtée ? | C60: QUOTIDIEN | D60: Boisson | E60: =COUNTIF(Questions!D:D,D60) -> 2
A61: Quel est ton cocktail préféré ? | C61: QUOTIDIEN | D61: Boisson | E61: =COUNTIF(Questions!D:D,D61) -> 2
A62: Quel sujet supposément marrant te fait pas trop rire ? | C62: EMOTIONS & BIEN-ÊTRE | D62: Bon délire | E62: =COUNTIF(Questions!D:D,D62) -> 2
A63: Quel est le truc/souvenir/sujet qui te fait assurément rire quand tu y penses, même seul ? | C63: EMOTIONS & BIEN-ÊTRE | D63: Bon délire | E63: =COUNTIF(Questions!D:D,D63) -> 2 | F63: reformuler
A64: Quel est le bruit naturel que tu adores écouter ? | C64: QUOTIDIEN | D64: Bruit | E64: =COUNTIF(Questions!D:D,D64) -> 2
A65: Si tu pouvais supprimer un bruit de l’existence, lequel choisirais-tu ? | C65: QUOTIDIEN | D65: Bruit | E65: =COUNTIF(Questions!D:D,D65) -> 2
A66: Quel est le cadeau typique de dernière minute que tu offres souvent ? | C66: FACE À TOI-MÊME | D66: Cadeaux Reçus | E66: =COUNTIF(Questions!D:D,D66) -> 2
A67: Quel est le pire cadeau que tu aies jamais reçu ? | C67: FACE À TOI-MÊME | D67: Cadeaux Reçus | E67: =COUNTIF(Questions!D:D,D67) -> 2
A68: Si tu pouvais offrir un cadeau à la personne de gauche sans limite de budget, que choisirais-tu ? | C68: ENTRE NOUS | D68: Cadeaux | E68: =COUNTIF(Questions!D:D,D68) -> 2
A69: Si la personne à droite t'offrait un cadeau, lequel serait-t'il ? | C69: ENTRE NOUS | D69: Cadeaux | E69: =COUNTIF(Questions!D:D,D69) -> 2
A70: Quel est le plus grand coup de chance que tu aies jamais eu ? | C70: FACE À TOI-MÊME | D70: Chance et malchance | E70: =COUNTIF(Questions!D:D,D70) -> 2
A71: Quel est le plus gros coup de malchance que tu penses avoir eu ? | C71: FACE À TOI-MÊME | D71: Chance et malchance | E71: =COUNTIF(Questions!D:D,D71) -> 2
A72: Quelle est la personne que tu trouves la plus stylée du groupe ? | C72: ENTRE NOUS | D72: Percée | E72: =COUNTIF(Questions!D:D,D72) -> 2 | F72: Trouver meilleur nom de type
A73: Qui aurait le plus de chances de devenir célèbre ? | C73: ENTRE NOUS | D73: Percée | E73: =COUNTIF(Questions!D:D,D73) -> 2
A74: Quelle est une célébrité qui t'a déçu ? | C74: PASSIONS & ACTIVITES | D74: Célébrité | E74: =COUNTIF(Questions!D:D,D74) -> 2
A75: Quelle est la dernière célébrité que tu as croisé dans la vraie vie ? | C75: PASSIONS & ACTIVITES | D75: Célébrité | E75: =COUNTIF(Questions!D:D,D75) -> 2
A76: Quel est ton meilleur souvenir de l'année ? | C76: RETOUR EN ARRIERE | D76: Cette année | E76: =COUNTIF(Questions!D:D,D76) -> 2
A77: Quel est ton pire moment de cette année ? | C77: RETOUR EN ARRIERE | D77: Cette année | E77: =COUNTIF(Questions!D:D,D77) -> 2
A78: Quelle est la chose que tu ne changeras jamais chez toi ? | C78: FACE À TOI-MÊME | D78: Choses à changer | E78: =COUNTIF(Questions!D:D,D78) -> 2
A79: Quelle est la chose que tu regrettes de ne pas avoir faite ? | C79: FACE À TOI-MÊME | D79: Choses à changer | E79: =COUNTIF(Questions!D:D,D79) -> 2
A80: Existe t'il un sujet ou tu es clairement pas objectif ? | C80: LES DOSSIERS | D80: Changements | E80: =COUNTIF(Questions!D:D,D80) -> 2
A81: Quel est le plus grand changement que tu aimerais voir dans le monde dans les 10 prochaines années ? | C81: LES DOSSIERS | D81: Changements | E81: =COUNTIF(Questions!D:D,D81) -> 2
A82: Si tu pouvais échanger ta vie avec quelqu'un du groupe pendant une semaine, qui choisirais-tu ? | C82: ENTRE NOUS | D82: Changements de vie | E82: =COUNTIF(Questions!D:D,D82) -> 2
A83: Qui a la vie qui te ressemble le plus ? | C83: ENTRE NOUS | D83: Changements de vie | E83: =COUNTIF(Questions!D:D,D83) -> 2
A84: Quelle est ta chanson nostalgie ? | C84: CINE & MUSIQUE | D84: Chanson nostalgie | E84: =COUNTIF(Questions!D:D,D84) -> 2
... A94: Quelle est ta collection d'objets la plus impressionnante ? | C94: PASSIONS & ACTIVITES | D94: Collection | E94: =COUNTIF(Questions!D:D,D94) -> 2
A95: Quelle est ta collection que peu de gens connaissent ? | C95: PASSIONS & ACTIVITES | D95: Collection | E95: =COUNTIF(Questions!D:D,D95) -> 2 | F95: 23
A96: Avec qui tu aimerais vivre en colocation ? | C96: QUOTIDIEN | D96: Colocation | E96: =COUNTIF(Questions!D:D,D96) -> 2
A97: Quelle est la pire habitude que tu aies supportée chez quelqu'un avec qui tu vivais ? | C97: QUOTIDIEN | D97: Colocation | E97: =COUNTIF(Questions!D:D,D97) -> 2
A98: Quel est ton moyen de communication préféré ? (SMS, Messages, Appels, Insta...) | C98: QUOTIDIEN | D98: Messages | E98: =COUNTIF(Questions!D:D,D98) -> 2
A99: En moyenne, combien de messages envoies-tu par jour ? | C99: QUOTIDIEN | D99: Messages | E99: =COUNTIF(Questions!D:D,D99) -> 2 | F99: BOF
A100: Quelle est la phrase que tu utilises pour clore une conversation qui s'éternise ? | C100: LES DOSSIERS | D100: Communications | E100: =COUNTIF(Questions!D:D,D100) -> 2
A101: Quelle est la plus grande contradiction entre ce que tu prônes et ce que tu fais réellement ? | C101: LES DOSSIERS | D101: Communications | E101: =COUNTIF(Questions!D:D,D101) -> 2
A102: Dans quel domaine tu te compares encore trop aux autres, même si tu sais que c'est contre-productif ? | C102: QUI ES-TU ? | D102: Comparaison | E102: =COUNTIF(Questions!D:D,D102) -> 2
A103: Quelle réussite de quelqu'un te donne envie de progresser ? | C103: QUI ES-TU ? | D103: Comparaison | E103: =COUNTIF(Questions!D:D,D103) -> 2
A104: Quel est le compliment qui t'a le plus touché(e) dans ta vie, et de qui venait t'il ? | C104: EMOTIONS & BIEN-ÊTRE | D104: Compliments | E104: =COUNTIF(Questions!D:D,D104) -> 2
A105: Quel est le compliment que tu fais souvent aux autres mais que tu n'arrives pas à t'appliquer à toi-même ? | C105: EMOTIONS & BIEN-ÊTRE | D105: Compliments | E105: =COUNTIF(Questions!D:D,D105) -> 2
A106: Quel comportement tu as quand tu es vramient amoureux ? | C106: EMOTIONS & BIEN-ÊTRE | D106: Sous le charme | E106: =COUNTIF(Questions!D:D,D106) -> 2
A107: Quel comportement pourrait te faire quitter le date en 10 secondes ? | C107: EMOTIONS & BIEN-ÊTRE | D107: Sous le charme | E107: =COUNTIF(Questions!D:D,D107) -> 2 | F107: 23
A108: Quel est le premier concert auquel tu as assisté ? | C108: CINE & MUSIQUE | D108: Concerts & Danse | E108: =COUNTIF(Questions!D:D,D108) -> 2
A109: Si tu pouvais maîtriser un style de danse, lequel choisirais-tu ? | C109: CINE & MUSIQUE | D109: Concerts & Danse | E109: =COUNTIF(Questions!D:D,D109) -> 2
A110: Qu'est-ce qui peut faire s'effondrer ta confiance en toi en quelques secondes ? | C110: QUI ES-TU ? | D110: Confiance | E110: =COUNTIF(Questions!D:D,D110) -> 2
A111: Quelle est la chose qui peut instantanément faire gagner ta confiance à quelqu'un ? | C111: QUI ES-TU ? | D111: Confiance | E111: =COUNTIF(Questions!D:D,D111) -> 2
A112: Quelle est la plus grosse connerie que tu aies faite ? | C112: LES DOSSIERS | D112: Conneries | E112: =COUNTIF(Questions!D:D,D112) -> 2
A113: Qui as-tu déjà poussé à la connerie, et qu'a-t-il fait ? | C113: LES DOSSIERS | D113: Conneries | E113: =COUNTIF(Questions!D:D,D113) -> 2 | F113: reformuler
A114: Quel est le conseil amoureux que tu donnerais à ton "moi" plus jeune ? | C114: EMOTIONS & BIEN-ÊTRE | D114: Conseils amoureux | E114: =COUNTIF(Questions!D:D,D114) -> 2
A115: Quelle est ta maxime en amour ? | C115: EMOTIONS & BIEN-ÊTRE | D115: Conseils amoureux | E115: =COUNTIF(Questions!D:D,D115) -> 2 | F115: 23
A116: Quel conseil donnerais-tu à ton toi plus jeune? | C116: RETOUR EN ARRIERE | D116: Plus Jeune | E116: =COUNTIF(Questions!D:D,D116) -> 2
A117: Qu'est-ce qui rendait ton toi d'enfant heureux et que tu as arrêté de faire adulte ? | C117: RETOUR EN ARRIERE | D117: Plus Jeune | E117: =COUNTIF(Questions!D:D,D117) -> 2
A118: Quel type de contenu préfères-tu voir sur les réseaux ? | C118: PASSIONS & ACTIVITES | D118: Contenu des réseaux | E118: =COUNTIF(Questions!D:D,D118) -> 2
A119: Quelle est la chose que tu postes le moins sur les réseaux mais qui représente le mieux ta vraie vie ? | C119: PASSIONS & ACTIVITES | D119: Contenu des réseaux | E119: =COUNTIF(Questions!D:D,D119) -> 2
A120: Quelle est la chose que tu possèdes (talent, trait, situation) et dont tu n'es pas assez fier(ère) ? | C120: FACE À TOI-MÊME | D120: Contradictions | E120: =COUNTIF(Questions!D:D,D120) -> 2
A121: Qu'est-ce qui est le + contradictoire entre tes envies et ta vie de tous les jours ? | C121: FACE À TOI-MÊME | D121: Contradictions | E121: =COUNTIF(Questions!D:D,D121) -> 2 | F121: 23
A122: Si tu pouvais avoir une conversation de 30 minutes avec n'importe qui au monde vivant aujourd'hui, qui serait-ce ? | C122: QUI ES-TU ? | D122: Conversations | E122: =COUNTIF(Questions!D:D,D122) -> 2
A123: Quelle est la conversation la plus dure que tu as eu à mener ? | C123: QUI ES-TU ? | D123: Conversations | E123: =COUNTIF(Questions!D:D,D123) -> 2 | F123: 23
A124: Quelle partie de ton corps tu aimes le plus, et pourquoi ? | C124: QUI ES-TU ? | D124: Corps | E124: =COUNTIF(Questions!D:D,D124) -> 2
A125: Quel est ton complexe physique ? | C125: QUI ES-TU ? | D125: Corps | E125: =COUNTIF(Questions!D:D,D125) -> 2
...

Sheet Nombre
A1: THEMES | B1: CATEGORIES | M1: Type de Question
A2: AMBITIONS | B2: DEEP | C2: =COUNTIF(Questions!C:C,Nombre!A2) -> 48 | E2: DEEP | F2: =COUNTIF(B:B,"DEEP") -> 4 | G2: =SUMIF(B:B,E2,C:C) -> 222 | M2: 5 sens | N2: =COUNTIF(Questions!D:D,Nombre!M2) -> 2 | Q2: Catégorie
A3: AMIS & FAMILLE | B3: FUN | C3: =COUNTIF(Questions!C:C,Nombre!A3) -> 40 | E3: FUN | F3: =COUNTIF(B:B,"FUN") -> 5 | G3: =SUMIF(B:B,E3,C:C) -> 168 | M3: A l'école | N3: =COUNTIF(Questions!D:D,Nombre!M86) -> 0 | Q3: Thème
A4: HOT | B4: FUN | C4: =COUNTIF(Questions!C:C,Nombre!A4) -> 16 | E4: ICEBREAKERS | F4: =COUNTIF(B:B,"ICEBREAKERS") -> 6 | G4: =SUMIF(B:B,E4,C:C) -> 282 | M4: A l'écolé | N4: =COUNTIF(Questions!D:D,Nombre!M85) -> 2 | Q4: Sujet
A5: CINE & MUSIQUE | B5: ICEBREAKERS | C5: =COUNTIF(Questions!C:C,Nombre!A5) -> 38 | M5: Achats | N5: =COUNTIF(Questions!D:D,Nombre!M3) -> 2
A6: ENTRE NOUS | B6: FUN | C6: =COUNTIF(Questions!C:C,Nombre!A6) -> 40 | M6: Activité | N6: =COUNTIF(Questions!D:D,Nombre!M4) -> 0
A7: FACE À TOI-MÊME | B7: DEEP | C7: =COUNTIF(Questions!C:C,Nombre!A7) -> 76 | H7: AMBITIONS | M7: Admirateur | N7: =COUNTIF(Questions!D:D,Nombre!M5) -> 2
A8: LES DOSSIERS | B8: FUN | C8: =COUNTIF(Questions!C:C,Nombre!A8) -> 52 | H8: AVENIR : | M8: Ambiance | N8: =COUNTIF(Questions!D:D,Nombre!M6) -> 2
A9: PASSIONS & ACTIVITES | B9: ICEBREAKERS | C9: =COUNTIF(Questions!C:C,Nombre!A9) -> 74 | M9: Amis perdus | N9: =COUNTIF(Questions!D:D,Nombre!M7) -> 2
A10: QUI ES-TU ? | B10: ICEBREAKERS | C10: =COUNTIF(Questions!C:C,Nombre!A10) -> 34 | M10: Amitié Durable | N10: =COUNTIF(Questions!D:D,Nombre!M8) -> 2
A11: QUOTIDIEN | B11: ICEBREAKERS | C11: =COUNTIF(Questions!C:C,Nombre!A11) -> 78 | M11: Amitié proche | N11: =COUNTIF(Questions!D:D,Nombre!M9) -> 2
A12: RETOUR EN ARRIERE | B12: DEEP | C12: =COUNTIF(Questions!C:C,Nombre!A12) -> 42 | M12: Amour propre | N12: =COUNTIF(Questions!D:D,Nombre!M10) -> 2
A13: VOYAGES & SORTIE | B13: ICEBREAKERS | C13: =COUNTIF(Questions!C:C,Nombre!A13) -> 38 | M13: Animal | N13: =COUNTIF(Questions!D:D,Nombre!M11) -> 2
A14: EMOTIONS & BIEN-ÊTRE | B14: DEEP | C14: =COUNTIF(Questions!C:C,Nombre!A14) -> 56 | M14: Animal de Compagnie | N14: =COUNTIF(Questions!D:D,Nombre!M12) -> 2
A15: MISE EN SITUATION | B15: ICEBREAKERS | C15: =COUNTIF(Questions!C:C,Nombre!A15) -> 20 | M15: Animation | N15: =COUNTIF(Questions!D:D,Nombre!M13) -> 2
A16: MES OPINIONS | B16: FUN | C16: =COUNTIF(Questions!C:C,Nombre!A16) -> 20 | M16: Anniversaire | N16: =COUNTIF(Questions!D:D,Nombre!M14) -> 2
C17: =COUNTIF(Questions!A2:A647,"") -> 0 | M17: Apparences trompeuses | N17: =COUNTIF(Questions!D:D,Nombre!M15) -> 2
C18: =SUM(C2:C17) -> 672 | M18: Architecture | N18: =COUNTIF(Questions!D:D,Nombre!M16) -> 2
M19: Art | N19: =COUNTIF(Questions!D:D,Nombre!M17) -> 2
M20: Aspirations profondes | N20: =COUNTIF(Questions!D:D,Nombre!M18) -> 2
M21: Astrologie | N21: =COUNTIF(Questions!D:D,Nombre!M19) -> 2
M22: Attentes | N22: =COUNTIF(Questions!D:D,Nombre!M20) -> 2
M23: Au dodo | N23: =COUNTIF(Questions!D:D,Nombre!M21) -> 2
M24: Au travail | N24: =COUNTIF(Questions!D:D,Nombre!M22) -> 2
M25: Autobiographie | N25: =COUNTIF(Questions!D:D,Nombre!M23) -> 2
M26: Avenir | N26: =COUNTIF(Questions!D:D,Nombre!M24) -> 2
M27: Aveux | N27: =COUNTIF(Questions!D:D,Nombre!M25) -> 2
M28: Blague | N28: =COUNTIF(Questions!D:D,Nombre!M27) -> 2
M29: Bodycount | N29: =COUNTIF(Questions!D:D,Nombre!M28) -> 2
M30: Boisson | N30: =COUNTIF(Questions!D:D,Nombre!M29) -> 2
M31: Bon délire | N31: =COUNTIF(Questions!D:D,Nombre!M30) -> 2
M32: Bruit | N32: =COUNTIF(Questions!D:D,Nombre!M31) -> 2
M33: Ca ME SOULE | N33: =COUNTIF(Questions!D:D,Nombre!M32) -> 2
M34: Cadeaux | N34: =COUNTIF(Questions!D:D,Nombre!M33) -> 0
M35: Cadeaux Reçus | N35: =COUNTIF(Questions!D:D,Nombre!M34) -> 2
M36: Célébrité | N36: =COUNTIF(Questions!D:D,Nombre!M35) -> 2
M37: Cette année | N37: =COUNTIF(Questions!D:D,Nombre!M36) -> 2
M38: Chance et malchance | N38: =COUNTIF(Questions!D:D,Nombre!M37) -> 2
M39: Changements | N39: =COUNTIF(Questions!D:D,Nombre!M38) -> 2
... M77: Destination | N77: =COUNTIF(Questions!D:D,Nombre!M76) -> 0
M78: Développement Perso | N78: =COUNTIF(Questions!D:D,Nombre!M78) -> 2
M79: Développements | N79: =COUNTIF(Questions!D:D,Nombre!M79) -> 2
M80: Discussions Idéales | N80: =COUNTIF(Questions!D:D,Nombre!M80) -> 2
M81: Discussions profondes | N81: =COUNTIF(Questions!D:D,Nombre!M77) -> 2
M82: Disney | N82: =COUNTIF(Questions!D:D,Nombre!M81) -> 2
M83: Disputes | N83: =COUNTIF(Questions!D:D,Nombre!M82) -> 2
M84: Drague | N84: =COUNTIF(Questions!D:D,Nombre!M84) -> 2
M85: Economies | N85: =COUNTIF(Questions!D:D,Nombre!M88) -> 2
M86: Écrans | N86: =COUNTIF(Questions!D:D,Nombre!M89) -> 2
M87: Écriture | N87: =COUNTIF(Questions!D:D,Nombre!M90) -> 2
M88: Embrouille | N88: =COUNTIF(Questions!D:D,Nombre!M91) -> 0
M89: En crise | N89: =COUNTIF(Questions!D:D,Nombre!M92) -> 2
M90: Endroits spécifiques | N90: =COUNTIF(Questions!D:D,Nombre!M93) -> 2
M91: Energie | N91: =COUNTIF(Questions!D:D,Nombre!M94) -> 2
M92: Énergie | N92: =COUNTIF(Questions!D:D,Nombre!M95) -> 2
M93: Enfance | N93: =COUNTIF(Questions!D:D,Nombre!M96) -> 2
M94: Engagement | N94: =COUNTIF(Questions!D:D,Nombre!M97) -> 2
M95: Enseignement | N95: =COUNTIF(Questions!D:D,Nombre!M98) -> 2
M96: Etudes | N96: =COUNTIF(Questions!D:D,Nombre!M87) -> 0
M97: Exagérations | N97: =COUNTIF(Questions!D:D,Nombre!M99) -> 2
M98: Expatriations | N98: =COUNTIF(Questions!D:D,Nombre!M100) -> 2
M99: Expériences de voyages | N99: =COUNTIF(Questions!D:D,Nombre!M101) -> 2
M100: Expériences Fondatrices | N100: =COUNTIF(Questions!D:D,Nombre!M102) -> 2
M101: Fail | N101: =COUNTIF(Questions!D:D,Nombre!M103) -> 2
M102: Famille | N102: =COUNTIF(Questions!D:D,Nombre!M104) -> 2
M103: Famille proche | N103: =COUNTIF(Questions!D:D,Nombre!M105) -> 2
M104: Famille secrète | N104: =COUNTIF(Questions!D:D,Nombre!M106) -> 2
M105: Fantasmes | N105: =COUNTIF(Questions!D:D,Nombre!M107) -> 2
M106: Fatigue | N106: =COUNTIF(Questions!D:D,Nombre!M108) -> 2
M107: Fête | N107: =COUNTIF(Questions!D:D,Nombre!M109) -> 2
M108: Fiction | N108: =COUNTIF(Questions!D:D,Nombre!M110) -> 0
... M261: Santé | N261: =COUNTIF(Questions!D:D,Nombre!M263) -> 2
M262: Santé mentale | N262: =COUNTIF(Questions!D:D,Nombre!M26) -> 2
M263: Scènes de films | N263: =COUNTIF(Questions!D:D,Nombre!M264) -> 2
M264: Secret du Groupe | N264: =COUNTIF(Questions!D:D,Nombre!M265) -> 0
M265: Série | N265: =COUNTIF(Questions!D:D,Nombre!M266) -> 2
M266: Sérieux ? | N266: =COUNTIF(Questions!D:D,Nombre!M267) -> 2
M267: Silences & Émotions | N267: =COUNTIF(Questions!D:D,Nombre!M268) -> 2
M268: Situations délicates | N268: =COUNTIF(Questions!D:D,Nombre!M269) -> 2
M269: Social | N269: =COUNTIF(Questions!D:D,Nombre!M270) -> 0
M270: Social | N270: =COUNTIF(Questions!D:D,Nombre!M271) -> 2
M271: Soirée | N271: =COUNTIF(Questions!D:D,Nombre!M272) -> 2
M272: Solitude | N272: =COUNTIF(Questions!D:D,Nombre!M273) -> 0
M273: Solitude | N273: =COUNTIF(Questions!D:D,Nombre!M274) -> 0
M274: Souvenir | N274: =COUNTIF(Questions!D:D,Nombre!M275) -> 2
... M295: Tes Passions | N295: =COUNTIF(Questions!D:D,Nombre!M296) -> 0
M296: Tombé | N296: =COUNTIF(Questions!D:D,Nombre!M83) -> 2
M297: Ton Look & Beauté | N297: =COUNTIF(Questions!D:D,Nombre!M297) -> 2
M298: Traditions Familiales | N298: =COUNTIF(Questions!D:D,Nombre!M298) -> 2
M299: Trajectoire de vie | N299: =COUNTIF(Questions!D:D,Nombre!M299) -> 2
M300: Transport | N300: =COUNTIF(Questions!D:D,Nombre!M300) -> 0
M301: Transports | N301: =COUNTIF(Questions!D:D,Nombre!M301) -> 2
M302: Trivia | N302: =COUNTIF(Questions!D:D,Nombre!M302) -> 2
M303: Trouvé | N303: =COUNTIF(Questions!D:D,Nombre!M303) -> 0
M304: TV | N304: =COUNTIF(Questions!D:D,Nombre!M304) -> 2
M305: Type de films | N305: =COUNTIF(Questions!D:D,Nombre!M305) -> 2
M306: Vacances | N306: =COUNTIF(Questions!D:D,Nombre!M306) -> 2
M307: Vériés | N307: =COUNTIF(Questions!D:D,Nombre!M307) -> 0
M308: Vérités | N308: =COUNTIF(Questions!D:D,Nombre!M308) -> 2
... M313: What | N313: =COUNTIF(Questions!D:D,Nombre!M313) -> 2

Sheet Noms Themes et Grilles
A1: AMBITIONS 🚀 Tes rêves, ton argent, ta vision ! Que veux-tu vraiment construire ?
A2: AMIS & FAMILLE🫂Des questions sur tes liens avec ceux qui comptent vraiment !
A3: HOT 🔞 En dehors des regards ! Pour les adultes uniquement
A4: CINÉ & MUSIQUE🎬Ce que tu écoutes, ce que tu regardes, ce que ça dit de toi sans que tu t'en rendes compte !
A5: ENTRE NOUS👀 Des questions sur la dynamique de groupe elle-même !
A6: FACE À TOI-MÊME🪞Pas de filtre : ce que tu sais de toi mais que tu dis rarement.
A7: LES DOSSIERS📂 Opinions tranchées, aveux gênants, Onskoné ou ou Onvastapé !
A8: PASSIONS & ACTIVITÉS🎯 Ce qui te fait vibrer dans la vie !
A9: QUI ES-TU ?🧬Ton introduction, et les premiers détails qui apprenent à savoir qui tu es !
A10: QUOTIDIEN☀️Le matin, les habitudes, les petits riens !
A11: RETOUR EN ARRIÈRE⏪L'enfance, les regrets, les tournants. Tout ce qui t'a construit !
A12: VOYAGES & SORTIE🌍 Ou tu vas et ou tu sors !
... A15: TES OPINIONS🗣️ Ce que tu penses à voix haute, sur plusieurs sujets particuliers !

Sheet 📊 Résumé
A1: Thème | B1: Nb Questions | C1: Nb Types
A2: AMBITIONS | B2: 44 | C2: 23
A3: AMIS & FAMILLE | B3: 30 | C3: 17
A4: AMOUR & SÉDUCTION | B4: 27 | C4: 14
A5: CINÉ & SÉRIES | B5: 27 | C5: 14
A6: ENTRE NOUS | B6: 33 | C6: 17
A7: FACE À TOI-MÊME | B7: 113 | C7: 57
A8: HUMOUR & DOSSIERS | B8: 47 | C8: 24
A9: LE MONDE | B9: 22 | C9: 11
A10: MUSIQUE | B10: 18 | C10: 10
A11: PASSIONS & CRÉA | B11: 98 | C11: 49
A12: QUI ES-TU ? | B12: 49 | C12: 26
A13: QUOTIDIEN | B13: 94 | C13: 49
... A17: TOTAL | B17: 705 | C17: 364
