Workbook

Sheet Questions
A1: Question | B1: Le Tip ! | C1: Thème | D1: Sujet | F1: Question Anglais | G1: Theme | H1: Sujet | J1: Remarques de Boubou
A2: Quelle est la première pensée que tu as au réveil la majorité des matins ? | C2: QUOTIDIEN | D2: Matin | E2: =COUNTIF(Questions!D:D,D2) -> 2 | F2: What's the first thought that goes through your mind when you wake up most mornings? | G2: DAILY LIFE | H2: Morning Routine | I2: =COUNTIF(Questions!H:H,H2) -> 2
A3: Si tu pouvais changer une chose dans ta routine matinale actuelle, ce serait quoi ? | C3: QUOTIDIEN | D3: Matin | E3: =COUNTIF(Questions!D:D,D3) -> 2 | F3: If you could change one thing about your current morning routine, what would it be? | G3: DAILY LIFE | H3: Morning Routine | I3: =COUNTIF(Questions!H:H,H3) -> 2
A4: Quelle est la personne la plus intelligente du groupe ? | C4: ENTRE NOUS | D4: Le meilleur | E4: =COUNTIF(Questions!D:D,D4) -> 2 | F4: Who's the most intelligent person in the group? | G4: BETWEEN US | H4: Best In Group | I4: =COUNTIF(Questions!H:H,H4) -> 2
A5: Qui est la personne la plus drôle du groupe ? | C5: ENTRE NOUS | D5: Le meilleur | E5: =COUNTIF(Questions!D:D,D5) -> 2 | F5: Who's the funniest person in the group? | G5: BETWEEN US | H5: Best In Group | I5: =COUNTIF(Questions!H:H,H5) -> 2
A6: Y a-t-il un moment de ta vie dont tu n'as aucun souvenir mais qu'on t'a souvent raconté ? | C6: RETOUR EN ARRIERE | D6: Moments de vie | E6: =COUNTIF(Questions!D:D,D6) -> 2 | F6: Is there a moment in your life you have no memory of, but that people have told you about many times? | G6: BACK IN THE DAY | H6: Life Moments | I6: =COUNTIF(Questions!H:H,H6) -> 2
A7: Quel moment de vie prenais-tu pour acquis et ne te satisfait pas, avant de te rendre compte qu'il était vraiment unique ? | C7: RETOUR EN ARRIERE | D7: Moments de vie | E7: =COUNTIF(Questions!D:D,D7) -> 2 | F7: What moment did you take for granted, only to later realize it was truly unique? | G7: BACK IN THE DAY | H7: Life Moments | I7: =COUNTIF(Questions!H:H,H7) -> 2 | J7: 23
A8: Quelle qualité partages tu avec ton voisin de gauche ? | C8: ENTRE NOUS | D8: Partage | E8: =COUNTIF(Questions!D:D,D8) -> 2 | F8: What quality do you share with the person on your left? | G8: BETWEEN US | H8: Sharing | I8: =COUNTIF(Questions!H:H,H8) -> 2
A9: Si tu devais offrir un cadeau à ton voisin de gauche, que lui donnerais-tu ? | C9: ENTRE NOUS | D9: Partage | E9: =COUNTIF(Questions!D:D,D9) -> 2 | F9: If you had to give a gift to the person on your left, what would you give them? | G9: BETWEEN US | H9: Sharing | I9: =COUNTIF(Questions!H:H,H9) -> 2
A10: Quel est ton sens le plus développé ? | C10: QUOTIDIEN | D10: 5 sens | E10: =COUNTIF(Questions!D:D,D10) -> 2 | F10: Which of your five senses is the most developed? | G10: DAILY LIFE | H10: The 5 Senses | I10: =COUNTIF(Questions!H:H,H10) -> 2
A11: Si tu perdais un sens pour toujours, lequel choisis-tu de sacrifier ? | C11: QUOTIDIEN | D11: 5 sens | E11: =COUNTIF(Questions!D:D,D11) -> 2 | F11: If you had to lose one sense forever, which one would you sacrifice? | G11: DAILY LIFE | H11: The 5 Senses | I11: =COUNTIF(Questions!H:H,H11) -> 2
A12: Quel est le mot qui résume toute ta période scolaire ? | C12: RETOUR EN ARRIERE | D12: A l'école | E12: =COUNTIF(Questions!D:D,D12) -> 2 | F12: What one word sums up your entire school life? | G12: BACK IN THE DAY | H12: School Days | I12: =COUNTIF(Questions!H:H,H12) -> 2
A13: Quelle était ta matière préférée à l'école ? | C13: RETOUR EN ARRIERE | D13: A l'école | E13: =COUNTIF(Questions!D:D,D13) -> 2 | F13: What was your favorite subject at school? | G13: BACK IN THE DAY | H13: School Days | I13: =COUNTIF(Questions!H:H,H13) -> 2
A14: Si tu gagnais à la loterie, quel serait ton premier achat ? | C14: AMBITIONS | D14: Achats | E14: =COUNTIF(Questions!D:D,D14) -> 2 | F14: If you won the lottery, what would be your first purchase? | G14: AMBITIONS | H14: Big Purchases | I14: =COUNTIF(Questions!H:H,H14) -> 2
A15: Quelle est la chose la plus chère que tu possèdes en terme de prix ? | C15: AMBITIONS | D15: Achats | E15: =COUNTIF(Questions!D:D,D15) -> 2 | F15: What's the most expensive thing you own? | G15: AMBITIONS | H15: Big Purchases | I15: =COUNTIF(Questions!H:H,H15) -> 2
A16: Quelle est l’activité manuelle que tu essayes d'apprendre actuellement ? | C16: PASSIONS & ACTIVITES | D16: Activité | E16: =COUNTIF(Questions!D:D,D16) -> 2 | F16: What manual skill are you currently trying to learn? | G16: HOBBIES & PASSIONS | H16: Activities | I16: =COUNTIF(Questions!H:H,H16) -> 2
A17: Quelle est l'activité qui te détend totalement ? | C17: PASSIONS & ACTIVITES | D17: Activité | E17: =COUNTIF(Questions!D:D,D17) -> 2 | F17: What activity completely relaxes you? | G17: HOBBIES & PASSIONS | H17: Activities | I17: =COUNTIF(Questions!H:H,H17) -> 2
A18: Quelle est la célébrité que tu trouves le plus BG ? | C18: CINE & MUSIQUE | D18: Admirateur | E18: =COUNTIF(Questions!D:D,D18) -> 2 | F18: Which celebrity do you find the most attractive? | G18: MOVIES & MUSIC | H18: Celebrity Crush | I18: =COUNTIF(Questions!H:H,H18) -> 2
A19: Si tu pouvais être n’importe quelle célébrité pendant une journée, qui serais-tu ? | C19: CINE & MUSIQUE | D19: Admirateur | E19: =COUNTIF(Questions!D:D,D19) -> 2 | F19: If you could be any celebrity for a day, who would you be? | G19: MOVIES & MUSIC | H19: Celebrity Crush | I19: =COUNTIF(Questions!H:H,H19) -> 2
... A32: Quel est le film d’animation qui te rappelle ton enfance ? | C32: CINE & MUSIQUE | D32: Animation | E32: =COUNTIF(Questions!D:D,D32) -> 2 | F32: Which animated film takes you back to your childhood? | G32: MOVIES & MUSIC | H32: Animated Films | I32: =COUNTIF(Questions!H:H,H32) -> 2
A33: Quel est le film d'animation le plus célèbre, que tu n'as-tu jamais vu ? | C33: CINE & MUSIQUE | D33: Animation | E33: =COUNTIF(Questions!D:D,D33) -> 2 | F33: What's the most famous animated film you've never actually seen? | G33: MOVIES & MUSIC | H33: Animated Films | I33: =COUNTIF(Questions!H:H,H33) -> 2 | J33: 23
A34: Comment tu aimes fêter ton anniversaire ? | C34: QUOTIDIEN | D34: Anniversaire | E34: =COUNTIF(Questions!D:D,D34) -> 2 | F34: How do you like to celebrate your birthday? | G34: DAILY LIFE | H34: Birthdays | I34: =COUNTIF(Questions!H:H,H34) -> 2
A35: Si tu pouvais choisir ton cadeau d'anniversaire parfait cette année, ce serait quoi ? | C35: QUOTIDIEN | D35: Anniversaire | E35: =COUNTIF(Questions!D:D,D35) -> 2 | F35: If you could choose your perfect birthday gift this year, what would it be? | G35: DAILY LIFE | H35: Birthdays | I35: =COUNTIF(Questions!H:H,H35) -> 2
A36: Qui du groupe a l'air le plus sérieux mais est en réalité le plus fou ? | C36: ENTRE NOUS | D36: Apparences trompeuses | E36: =COUNTIF(Questions!D:D,D36) -> 2 | F36: Who in the group seems the most serious but is actually the most wild? | G36: BETWEEN US | H36: Surprising Appearances | I36: =COUNTIF(Questions!H:H,H36) -> 2
A37: Qui du groupe a l'air le plus intelligent, mais est en vrai le plus con ? | C37: ENTRE NOUS | D37: Apparences trompeuses | E37: =COUNTIF(Questions!D:D,D37) -> 2 | F37: Who in the group seems the most intelligent but is actually the least? | G37: BETWEEN US | H37: Surprising Appearances | I37: =COUNTIF(Questions!H:H,H37) -> 2
A38: Si tu pouvais concevoir ta maison idéale, comment elle serait ? | C38: PASSIONS & ACTIVITES | D38: Architecture | E38: =COUNTIF(Questions!D:D,D38) -> 2 | F38: If you could design your dream home, what would it look like? | G38: HOBBIES & PASSIONS | H38: Architecture | I38: =COUNTIF(Questions!H:H,H38) -> 2
A39: Quel est le bâtiment ou lieu que tu trouves le plus beau dans le monde ? | C39: PASSIONS & ACTIVITES | D39: Architecture | E39: =COUNTIF(Questions!D:D,D39) -> 2 | F39: What building or place do you find the most beautiful in the world? | G39: HOBBIES & PASSIONS | H39: Architecture | I39: =COUNTIF(Questions!H:H,H39) -> 2
A40: Si tu pouvais maîtriser parfaitement une forme d'art, laquelle choisirais-tu ? | C40: PASSIONS & ACTIVITES | D40: Art | E40: =COUNTIF(Questions!D:D,D40) -> 2 | F40: If you could master any art form perfectly, which one would you choose? | G40: HOBBIES & PASSIONS | H40: Art | I40: =COUNTIF(Questions!H:H,H40) -> 2
A41: Quelle œuvre d'art (tableau, sculpture, photo...) t'a un jour laissé sans voix ? | C41: PASSIONS & ACTIVITES | D41: Art | E41: =COUNTIF(Questions!D:D,D41) -> 2 | F41: What work of art (painting, sculpture, photo...) once left you speechless? | G41: HOBBIES & PASSIONS | H41: Art | I41: =COUNTIF(Questions!H:H,H41) -> 2
A42: Quelle est la vision de toi-même dans 10 ans que tu portes mais n'avoues à presque personne ? | C42: AMBITIONS | D42: Aspirations profondes | E42: =COUNTIF(Questions!D:D,D42) -> 2 | F42: What vision of yourself in 10 years do you carry but almost never tell anyone? | G42: AMBITIONS | H42: Deep Aspirations | I42: =COUNTIF(Questions!H:H,H42) -> 2
A43: Si l'argent et le regard des autres n'existaient pas, comment passerais-tu tes journées ? | C43: AMBITIONS | D43: Aspirations profondes | E43: =COUNTIF(Questions!D:D,D43) -> 2 | F43: If money and other people's opinions didn't exist, how would you spend your days? | G43: AMBITIONS | H43: Deep Aspirations | I43: =COUNTIF(Questions!H:H,H43) -> 2
A44: Quel est ton signe astrologique et est-ce que tu y crois ? Exemple de réponse : Scorpion/Oui | C44: QUI ES-TU ? | D44: Astrologie | E44: =COUNTIF(Questions!D:D,D44) -> 2 | F44: What's your star sign and do you believe in it? Example answer: Scorpio/Yes | G44: ABOUT YOU | H44: Astrology | I44: =COUNTIF(Questions!H:H,H44) -> 2
A45: Quelle est la superstitition à laquelle tu crois ? | C45: QUI ES-TU ? | D45: Astrologie | E45: =COUNTIF(Questions!D:D,D45) -> 2 | F45: What superstition do you actually believe in? | G45: ABOUT YOU | H45: Astrology | I45: =COUNTIF(Questions!H:H,H45) -> 2
... A50: Quel serait le titre de ton autobiographie ? | C50: RETOUR EN ARRIERE | D50: Autobiographie | E50: =COUNTIF(Questions!D:D,D50) -> 2 | F50: What would the title of your autobiography be? | G50: BACK IN THE DAY | H50: Your Autobiography | I50: =COUNTIF(Questions!H:H,H50) -> 2
A51: C'est le moment d'écrire un livre sur la vie de quelqu'un, sur qui tu l'écris ? | C51: RETOUR EN ARRIERE | D51: Autobiographie | E51: =COUNTIF(Questions!D:D,D51) -> 2 | F51: If you had to write a book about someone's life, whose would it be? | G51: BACK IN THE DAY | H51: Your Autobiography | I51: =COUNTIF(Questions!H:H,H51) -> 2 | J51: 23
A52: Quel aspect ou défi de la vie future te fait le plus peur ? | C52: AMBITIONS | D52: Avenir | E52: =COUNTIF(Questions!D:D,D52) -> 2 | F52: What aspect or challenge of the future scares you the most? | G52: AMBITIONS | H52: The Future | I52: =COUNTIF(Questions!H:H,H52) -> 2
A53: Quels sont les trois mots qui te viennent à l'esprit quand tu penses à l'avenir ? | C53: AMBITIONS | D53: Avenir | E53: =COUNTIF(Questions!D:D,D53) -> 2 | F53: What three words come to mind when you think about the future? | G53: AMBITIONS | H53: The Future | I53: =COUNTIF(Questions!H:H,H53) -> 2
A54: Quelle est la théorie du complot à laquelle tu adhères secrètement ? | C54: LES DOSSIERS | D54: Aveux | E54: =COUNTIF(Questions!D:D,D54) -> 2 | F54: What conspiracy theory do you secretly believe in? | G54: THE RECEIPTS | H54: Confessions | I54: =COUNTIF(Questions!H:H,H54) -> 2
A55: Quelle opinion impopulaire assumes-tu complètement ? | C55: LES DOSSIERS | D55: Aveux | E55: =COUNTIF(Questions!D:D,D55) -> 2 | F55: What unpopular opinion do you fully stand by? | G55: THE RECEIPTS | H55: Confessions | I55: =COUNTIF(Questions!H:H,H55) -> 2
A56: Quel type d'humour te fait vraiment rire ? | C56: LES DOSSIERS | D56: Blague | E56: =COUNTIF(Questions!D:D,D56) -> 2 | F56: What type of humor actually makes you laugh? | G56: THE RECEIPTS | H56: Jokes | I56: =COUNTIF(Questions!H:H,H56) -> 2
A57: Raconte-nous ta meilleure blague ? | C57: LES DOSSIERS | D57: Blague | E57: =COUNTIF(Questions!D:D,D57) -> 2 | F57: Tell us your best joke. | G57: THE RECEIPTS | H57: Jokes | I57: =COUNTIF(Questions!H:H,H57) -> 2
A58: Avec combien de personnes différentes as-tu couché ? | C58: HOT | D58: Bodycount | E58: =COUNTIF(Questions!D:D,D58) -> 2 | F58: How many different people have you slept with? | G58: SPICYYY | H58: Body Count | I58: =COUNTIF(Questions!H:H,H58) -> 2
A59: A quel âge as-tu eu ta première relation ? | C59: HOT | D59: Bodycount | E59: =COUNTIF(Questions!D:D,D59) -> 2 | F59: How old were you when you had your first relationship? | G59: SPICYYY | H59: Body Count | I59: =COUNTIF(Questions!H:H,H59) -> 2
A60: Quelle est la boisson la plus originale ou étrange que tu aies goûtée ? | C60: QUOTIDIEN | D60: Boisson | E60: =COUNTIF(Questions!D:D,D60) -> 2 | F60: What's the most original or strange drink you've ever tasted? | G60: DAILY LIFE | H60: Drinks | I60: =COUNTIF(Questions!H:H,H60) -> 2
A61: Quel est ton cocktail préféré ? | C61: QUOTIDIEN | D61: Boisson | E61: =COUNTIF(Questions!D:D,D61) -> 2 | F61: What's your favorite cocktail? | G61: DAILY LIFE | H61: Drinks | I61: =COUNTIF(Questions!H:H,H61) -> 2
A62: Quel sujet supposément marrant te fait pas trop rire ? | C62: EMOTIONS & BIEN-ÊTRE | D62: Bon délire | E62: =COUNTIF(Questions!D:D,D62) -> 2 | F62: What supposedly funny topic actually doesn't make you laugh that much? | G62: FEELINGS | H62: Good Laughs | I62: =COUNTIF(Questions!H:H,H62) -> 2
A63: Quel est le truc/souvenir/sujet qui te fait assurément rire quand tu y penses, même seul ? | C63: EMOTIONS & BIEN-ÊTRE | D63: Bon délire | E63: =COUNTIF(Questions!D:D,D63) -> 2 | F63: What memory or topic is guaranteed to make you laugh even when you're alone? | G63: FEELINGS | H63: Good Laughs | I63: =COUNTIF(Questions!H:H,H63) -> 2 | J63: reformuler
A64: Quel est le bruit naturel que tu adores écouter ? | C64: QUOTIDIEN | D64: Bruit | E64: =COUNTIF(Questions!D:D,D64) -> 2 | F64: What natural sound do you love to listen to? | G64: DAILY LIFE | H64: Sounds | I64: =COUNTIF(Questions!H:H,H64) -> 2
A65: Si tu pouvais supprimer un bruit de l’existence, lequel choisirais-tu ? | C65: QUOTIDIEN | D65: Bruit | E65: =COUNTIF(Questions!D:D,D65) -> 2 | F65: If you could remove one sound from existence, which one would you choose? | G65: DAILY LIFE | H65: Sounds | I65: =COUNTIF(Questions!H:H,H65) -> 2
A66: Quel est le cadeau typique de dernière minute que tu offres souvent ? | C66: FACE À TOI-MÊME | D66: Cadeaux Reçus | E66: =COUNTIF(Questions!D:D,D66) -> 2 | F66: What's the typical last-minute gift you often give people? | G66: IN THE MIRROR | H66: Gifts Received | I66: =COUNTIF(Questions!H:H,H66) -> 2
A67: Quel est le pire cadeau que tu aies jamais reçu ? | C67: FACE À TOI-MÊME | D67: Cadeaux Reçus | E67: =COUNTIF(Questions!D:D,D67) -> 2 | F67: What's the worst gift you've ever received? | G67: IN THE MIRROR | H67: Gifts Received | I67: =COUNTIF(Questions!H:H,H67) -> 2
A68: Si tu pouvais offrir un cadeau à la personne de gauche sans limite de budget, que choisirais-tu ? | C68: ENTRE NOUS | D68: Cadeaux | E68: =COUNTIF(Questions!D:D,D68) -> 2 | F68: If you could give a gift to the person on your left with no budget limit, what would you choose? | G68: BETWEEN US | H68: Gifts | I68: =COUNTIF(Questions!H:H,H68) -> 2
A69: Si la personne à droite t'offrait un cadeau, lequel serait-t'il ? | C69: ENTRE NOUS | D69: Cadeaux | E69: =COUNTIF(Questions!D:D,D69) -> 2 | F69: If the person on your right gave you a gift, what would it be? | G69: BETWEEN US | H69: Gifts | I69: =COUNTIF(Questions!H:H,H69) -> 2
A70: Quel est le plus grand coup de chance que tu aies jamais eu ? | C70: FACE À TOI-MÊME | D70: Chance et malchance | E70: =COUNTIF(Questions!D:D,D70) -> 2 | F70: What's the biggest stroke of luck you've ever had? | G70: IN THE MIRROR | H70: Luck & Bad Luck | I70: =COUNTIF(Questions!H:H,H70) -> 2
A71: Quel est le plus gros coup de malchance que tu penses avoir eu ? | C71: FACE À TOI-MÊME | D71: Chance et malchance | E71: =COUNTIF(Questions!D:D,D71) -> 2 | F71: What's the biggest stroke of bad luck you think you've had? | G71: IN THE MIRROR | H71: Luck & Bad Luck | I71: =COUNTIF(Questions!H:H,H71) -> 2
A72: Quelle est la personne que tu trouves la plus stylée du groupe ? | C72: ENTRE NOUS | D72: Percée | E72: =COUNTIF(Questions!D:D,D72) -> 2 | F72: Who in the group has the best style? | G72: BETWEEN US | H72: Breakthroughs | I72: =COUNTIF(Questions!H:H,H72) -> 2 | J72: Trouver meilleur nom de type
A73: Qui aurait le plus de chances de devenir célèbre ? | C73: ENTRE NOUS | D73: Percée | E73: =COUNTIF(Questions!D:D,D73) -> 2 | F73: Who in the group is most likely to become famous? | G73: BETWEEN US | H73: Breakthroughs | I73: =COUNTIF(Questions!H:H,H73) -> 2
A74: Quelle est une célébrité qui t'a déçu ? | C74: PASSIONS & ACTIVITES | D74: Célébrité | E74: =COUNTIF(Questions!D:D,D74) -> 2 | F74: Which celebrity has disappointed you? | G74: HOBBIES & PASSIONS | H74: Celebrities | I74: =COUNTIF(Questions!H:H,H74) -> 2
A75: Quelle est la dernière célébrité que tu as croisé dans la vraie vie ? | C75: PASSIONS & ACTIVITES | D75: Célébrité | E75: =COUNTIF(Questions!D:D,D75) -> 2 | F75: What's the last celebrity you spotted in real life? | G75: HOBBIES & PASSIONS | H75: Celebrities | I75: =COUNTIF(Questions!H:H,H75) -> 2
A76: Quel est ton meilleur souvenir de l'année ? | C76: RETOUR EN ARRIERE | D76: Cette année | E76: =COUNTIF(Questions!D:D,D76) -> 2 | F76: What's your best memory from this year? | G76: BACK IN THE DAY | H76: This Year | I76: =COUNTIF(Questions!H:H,H76) -> 2
A77: Quel est ton pire moment de cette année ? | C77: RETOUR EN ARRIERE | D77: Cette année | E77: =COUNTIF(Questions!D:D,D77) -> 2 | F77: What's your worst moment this year? | G77: BACK IN THE DAY | H77: This Year | I77: =COUNTIF(Questions!H:H,H77) -> 2
A78: Quelle est la chose que tu ne changeras jamais chez toi ? | C78: FACE À TOI-MÊME | D78: Choses à changer | E78: =COUNTIF(Questions!D:D,D78) -> 2 | F78: What's the one thing about yourself you'll never change? | G78: IN THE MIRROR | H78: Things to Change | I78: =COUNTIF(Questions!H:H,H78) -> 2
A79: Quelle est la chose que tu regrettes de ne pas avoir faite ? | C79: FACE À TOI-MÊME | D79: Choses à changer | E79: =COUNTIF(Questions!D:D,D79) -> 2 | F79: What's something you regret not having done? | G79: IN THE MIRROR | H79: Things to Change | I79: =COUNTIF(Questions!H:H,H79) -> 2
A80: Existe t'il un sujet ou tu es clairement pas objectif ? | C80: LES DOSSIERS | D80: Changements | E80: =COUNTIF(Questions!D:D,D80) -> 2 | F80: Is there a topic where you're clearly not objective? | G80: THE RECEIPTS | H80: Changes | I80: =COUNTIF(Questions!H:H,H80) -> 2
A81: Quel est le plus grand changement que tu aimerais voir dans le monde dans les 10 prochaines années ? | C81: LES DOSSIERS | D81: Changements | E81: =COUNTIF(Questions!D:D,D81) -> 2 | F81: What's the biggest change you'd like to see in the world in the next 10 years? | G81: THE RECEIPTS | H81: Changes | I81: =COUNTIF(Questions!H:H,H81) -> 2
A82: Si tu pouvais échanger ta vie avec quelqu'un du groupe pendant une semaine, qui choisirais-tu ? | C82: ENTRE NOUS | D82: Changements de vie | E82: =COUNTIF(Questions!D:D,D82) -> 2 | F82: If you could swap lives with someone in the group for a week, who would you choose? | G82: BETWEEN US | H82: Life Changes | I82: =COUNTIF(Questions!H:H,H82) -> 2
A83: Qui a la vie qui te ressemble le plus ? | C83: ENTRE NOUS | D83: Changements de vie | E83: =COUNTIF(Questions!D:D,D83) -> 2 | F83: Who has the life most similar to yours? | G83: BETWEEN US | H83: Life Changes | I83: =COUNTIF(Questions!H:H,H83) -> 2
A84: Quelle est ta chanson nostalgie ? | C84: CINE & MUSIQUE | D84: Chanson nostalgie | E84: =COUNTIF(Questions!D:D,D84) -> 2 | F84: What's your nostalgia song? | G84: MOVIES & MUSIC | H84: Nostalgia Songs | I84: =COUNTIF(Questions!H:H,H84) -> 2
... A94: Quelle est ta collection d'objets la plus impressionnante ? | C94: PASSIONS & ACTIVITES | D94: Collection | E94: =COUNTIF(Questions!D:D,D94) -> 2 | F94: What's your most impressive collection of objects? | G94: HOBBIES & PASSIONS | H94: Collections | I94: =COUNTIF(Questions!H:H,H94) -> 2
A95: Quelle est ta collection que peu de gens connaissent ? | C95: PASSIONS & ACTIVITES | D95: Collection | E95: =COUNTIF(Questions!D:D,D95) -> 2 | F95: What's a collection you have that few people know about? | G95: HOBBIES & PASSIONS | H95: Collections | I95: =COUNTIF(Questions!H:H,H95) -> 2 | J95: 23
A96: Avec qui tu aimerais vivre en colocation ? | C96: QUOTIDIEN | D96: Colocation | E96: =COUNTIF(Questions!D:D,D96) -> 2 | F96: Who would you want to live with as a roommate? | G96: DAILY LIFE | H96: Living Together | I96: =COUNTIF(Questions!H:H,H96) -> 2
A97: Quelle est la pire habitude que tu aies supportée chez quelqu'un avec qui tu vivais ? | C97: QUOTIDIEN | D97: Colocation | E97: =COUNTIF(Questions!D:D,D97) -> 2 | F97: What's the worst habit you've had to put up with from someone you lived with? | G97: DAILY LIFE | H97: Living Together | I97: =COUNTIF(Questions!H:H,H97) -> 2
A98: Quel est ton moyen de communication préféré ? (SMS, Messages, Appels, Insta...) | C98: QUOTIDIEN | D98: Messages | E98: =COUNTIF(Questions!D:D,D98) -> 2 | F98: What's your preferred way to communicate? (SMS, Messaging apps, Calls, Instagram...) | G98: DAILY LIFE | H98: Messaging | I98: =COUNTIF(Questions!H:H,H98) -> 2
A99: En moyenne, combien de messages envoies-tu par jour ? | C99: QUOTIDIEN | D99: Messages | E99: =COUNTIF(Questions!D:D,D99) -> 2 | F99: On average, how many messages do you send per day? | G99: DAILY LIFE | H99: Messaging | I99: =COUNTIF(Questions!H:H,H99) -> 2 | J99: BOF
A100: Quelle est la phrase que tu utilises pour clore une conversation qui s'éternise ? | C100: LES DOSSIERS | D100: Communications | E100: =COUNTIF(Questions!D:D,D100) -> 2 | F100: What phrase do you use to end a conversation that's going on too long? | G100: THE RECEIPTS | H100: Communication | I100: =COUNTIF(Questions!H:H,H100) -> 2
A101: Quelle est la plus grande contradiction entre ce que tu prônes et ce que tu fais réellement ? | C101: LES DOSSIERS | D101: Communications | E101: =COUNTIF(Questions!D:D,D101) -> 2 | F101: What's the biggest contradiction between what you preach and what you actually do? | G101: THE RECEIPTS | H101: Communication | I101: =COUNTIF(Questions!H:H,H101) -> 2
A102: Dans quel domaine tu te compares encore trop aux autres, même si tu sais que c'est contre-productif ? | C102: QUI ES-TU ? | D102: Comparaison | E102: =COUNTIF(Questions!D:D,D102) -> 2 | F102: In what area do you still compare yourself to others too much, even knowing it's counterproductive? | G102: ABOUT YOU | H102: Comparisons | I102: =COUNTIF(Questions!H:H,H102) -> 2
A103: Quelle réussite de quelqu'un te donne envie de progresser ? | C103: QUI ES-TU ? | D103: Comparaison | E103: =COUNTIF(Questions!D:D,D103) -> 2 | F103: Whose success genuinely motivates you to grow? | G103: ABOUT YOU | H103: Comparisons | I103: =COUNTIF(Questions!H:H,H103) -> 2
A104: Quel est le compliment qui t'a le plus touché(e) dans ta vie, et de qui venait t'il ? | C104: EMOTIONS & BIEN-ÊTRE | D104: Compliments | E104: =COUNTIF(Questions!D:D,D104) -> 2 | F104: What's the compliment that touched you the most in your life, and who gave it? | G104: FEELINGS | H104: Compliments | I104: =COUNTIF(Questions!H:H,H104) -> 2
A105: Quel est le compliment que tu fais souvent aux autres mais que tu n'arrives pas à t'appliquer à toi-même ? | C105: EMOTIONS & BIEN-ÊTRE | D105: Compliments | E105: =COUNTIF(Questions!D:D,D105) -> 2 | F105: What compliment do you often give others but can't seem to apply to yourself? | G105: FEELINGS | H105: Compliments | I105: =COUNTIF(Questions!H:H,H105) -> 2
A106: Quel comportement tu as quand tu es vramient amoureux ? | C106: EMOTIONS & BIEN-ÊTRE | D106: Sous le charme | E106: =COUNTIF(Questions!D:D,D106) -> 2 | F106: How do you behave when you're genuinely falling for someone? | G106: FEELINGS | H106: Under the Spell | I106: =COUNTIF(Questions!H:H,H106) -> 2
A107: Quel comportement pourrait te faire quitter le date en 10 secondes ? | C107: EMOTIONS & BIEN-ÊTRE | D107: Sous le charme | E107: =COUNTIF(Questions!D:D,D107) -> 2 | F107: What behavior would make you leave a date within 10 seconds? | G107: FEELINGS | H107: Under the Spell | I107: =COUNTIF(Questions!H:H,H107) -> 2 | J107: 23
A108: Quel est le premier concert auquel tu as assisté ? | C108: CINE & MUSIQUE | D108: Concerts & Danse | E108: =COUNTIF(Questions!D:D,D108) -> 2 | F108: What was the first concert you ever attended? | G108: MOVIES & MUSIC | H108: Concerts & Dancing | I108: =COUNTIF(Questions!H:H,H108) -> 2
A109: Si tu pouvais maîtriser un style de danse, lequel choisirais-tu ? | C109: CINE & MUSIQUE | D109: Concerts & Danse | E109: =COUNTIF(Questions!D:D,D109) -> 2 | F109: If you could master any dance style, which one would you choose? | G109: MOVIES & MUSIC | H109: Concerts & Dancing | I109: =COUNTIF(Questions!H:H,H109) -> 2
A110: Qu'est-ce qui peut faire s'effondrer ta confiance en toi en quelques secondes ? | C110: QUI ES-TU ? | D110: Confiance | E110: =COUNTIF(Questions!D:D,D110) -> 2 | F110: What can shatter your self-confidence in a matter of seconds? | G110: ABOUT YOU | H110: Trust | I110: =COUNTIF(Questions!H:H,H110) -> 2
A111: Quelle est la chose qui peut instantanément faire gagner ta confiance à quelqu'un ? | C111: QUI ES-TU ? | D111: Confiance | E111: =COUNTIF(Questions!D:D,D111) -> 2 | F111: What instantly earns someone your trust? | G111: ABOUT YOU | H111: Trust | I111: =COUNTIF(Questions!H:H,H111) -> 2
A112: Quelle est la plus grosse connerie que tu aies faite ? | C112: LES DOSSIERS | D112: Conneries | E112: =COUNTIF(Questions!D:D,D112) -> 2 | F112: What's the biggest stupid thing you've ever done? | G112: THE RECEIPTS | H112: Stupid Stuff | I112: =COUNTIF(Questions!H:H,H112) -> 2
A113: Qui as-tu déjà poussé à la connerie, et qu'a-t-il fait ? | C113: LES DOSSIERS | D113: Conneries | E113: =COUNTIF(Questions!D:D,D113) -> 2 | F113: Who have you led into doing something dumb, and what did they do? | G113: THE RECEIPTS | H113: Stupid Stuff | I113: =COUNTIF(Questions!H:H,H113) -> 2 | J113: reformuler
A114: Quel est le conseil amoureux que tu donnerais à ton "moi" plus jeune ? | C114: EMOTIONS & BIEN-ÊTRE | D114: Conseils amoureux | E114: =COUNTIF(Questions!D:D,D114) -> 2 | F114: What love advice would you give to your younger self? | G114: FEELINGS | H114: Love Advice | I114: =COUNTIF(Questions!H:H,H114) -> 2
A115: Quelle est ta maxime en amour ? | C115: EMOTIONS & BIEN-ÊTRE | D115: Conseils amoureux | E115: =COUNTIF(Questions!D:D,D115) -> 2 | F115: What's your personal motto when it comes to love? | G115: FEELINGS | H115: Love Advice | I115: =COUNTIF(Questions!H:H,H115) -> 2 | J115: 23
A116: Quel conseil donnerais-tu à ton toi plus jeune? | C116: RETOUR EN ARRIERE | D116: Plus Jeune | E116: =COUNTIF(Questions!D:D,D116) -> 2 | F116: What advice would you give to your younger self? | G116: BACK IN THE DAY | H116: Younger Self | I116: =COUNTIF(Questions!H:H,H116) -> 2
A117: Qu'est-ce qui rendait ton toi d'enfant heureux et que tu as arrêté de faire adulte ? | C117: RETOUR EN ARRIERE | D117: Plus Jeune | E117: =COUNTIF(Questions!D:D,D117) -> 2 | F117: What made your childhood self happy that you've stopped doing as an adult? | G117: BACK IN THE DAY | H117: Younger Self | I117: =COUNTIF(Questions!H:H,H117) -> 2
A118: Quel type de contenu préfères-tu voir sur les réseaux ? | C118: PASSIONS & ACTIVITES | D118: Contenu des réseaux | E118: =COUNTIF(Questions!D:D,D118) -> 2 | F118: What type of content do you prefer to see on social media? | G118: HOBBIES & PASSIONS | H118: Social Media Content | I118: =COUNTIF(Questions!H:H,H118) -> 2
A119: Quelle est la chose que tu postes le moins sur les réseaux mais qui représente le mieux ta vraie vie ? | C119: PASSIONS & ACTIVITES | D119: Contenu des réseaux | E119: =COUNTIF(Questions!D:D,D119) -> 2 | F119: What do you post least on social media, but that best represents your real life? | G119: HOBBIES & PASSIONS | H119: Social Media Content | I119: =COUNTIF(Questions!H:H,H119) -> 2
A120: Quelle est la chose que tu possèdes (talent, trait, situation) et dont tu n'es pas assez fier(ère) ? | C120: FACE À TOI-MÊME | D120: Contradictions | E120: =COUNTIF(Questions!D:D,D120) -> 2 | F120: What do you have (a talent, trait, or situation) that you're not proud enough of? | G120: IN THE MIRROR | H120: Contradictions | I120: =COUNTIF(Questions!H:H,H120) -> 2
A121: Qu'est-ce qui est le + contradictoire entre tes envies et ta vie de tous les jours ? | C121: FACE À TOI-MÊME | D121: Contradictions | E121: =COUNTIF(Questions!D:D,D121) -> 2 | F121: What's the biggest contradiction between what you want and your everyday life? | G121: IN THE MIRROR | H121: Contradictions | I121: =COUNTIF(Questions!H:H,H121) -> 2 | J121: 23
A122: Si tu pouvais avoir une conversation de 30 minutes avec n'importe qui au monde vivant aujourd'hui, qui serait-ce ? | C122: QUI ES-TU ? | D122: Conversations | E122: =COUNTIF(Questions!D:D,D122) -> 2 | F122: If you could have a 30-minute conversation with anyone alive in the world today, who would it be? | G122: ABOUT YOU | H122: Conversations | I122: =COUNTIF(Questions!H:H,H122) -> 2
A123: Quelle est la conversation la plus dure que tu as eu à mener ? | C123: QUI ES-TU ? | D123: Conversations | E123: =COUNTIF(Questions!D:D,D123) -> 2 | F123: What's the hardest conversation you've ever had to have? | G123: ABOUT YOU | H123: Conversations | I123: =COUNTIF(Questions!H:H,H123) -> 2 | J123: 23
A124: Quelle partie de ton corps tu aimes le plus, et pourquoi ? | C124: QUI ES-TU ? | D124: Corps | E124: =COUNTIF(Questions!D:D,D124) -> 2 | F124: What part of your body do you love the most, and why? | G124: ABOUT YOU | H124: Your Body | I124: =COUNTIF(Questions!H:H,H124) -> 2
A125: Quel est ton complexe physique ? | C125: QUI ES-TU ? | D125: Corps | E125: =COUNTIF(Questions!D:D,D125) -> 2 | F125: What's your biggest physical insecurity? | G125: ABOUT YOU | H125: Your Body | I125: =COUNTIF(Questions!H:H,H125) -> 2
...

Sheet Nombre
A1: THEMES | B1: CATEGORIES | M1: Type de Question
A2: AMBITIONS | B2: DEEP | C2: =COUNTIF(Questions!C:C,Nombre!A2) -> 48 | E2: DEEP | F2: =COUNTIF(B:B,"DEEP") -> 4 | G2: =SUMIF(B:B,E2,C:C) -> 220 | M2: 5 sens | N2: =COUNTIF(Questions!D:D,Nombre!M2) -> 2 | Q2: Catégorie
A3: AMIS & FAMILLE | B3: FUN | C3: =COUNTIF(Questions!C:C,Nombre!A3) -> 40 | E3: FUN | F3: =COUNTIF(B:B,"FUN") -> 5 | G3: =SUMIF(B:B,E3,C:C) -> 170 | M3: A l'école | N3: =COUNTIF(Questions!D:D,Nombre!M86) -> 0 | Q3: Thème
A4: HOT | B4: FUN | C4: =COUNTIF(Questions!C:C,Nombre!A4) -> 16 | E4: ICEBREAKERS | F4: =COUNTIF(B:B,"ICEBREAKERS") -> 6 | G4: =SUMIF(B:B,E4,C:C) -> 288 | M4: A l'écolé | N4: =COUNTIF(Questions!D:D,Nombre!M85) -> 2 | Q4: Sujet
A5: CINE & MUSIQUE | B5: ICEBREAKERS | C5: =COUNTIF(Questions!C:C,Nombre!A5) -> 38 | M5: Achats | N5: =COUNTIF(Questions!D:D,Nombre!M3) -> 2
A6: ENTRE NOUS | B6: FUN | C6: =COUNTIF(Questions!C:C,Nombre!A6) -> 40 | M6: Activité | N6: =COUNTIF(Questions!D:D,Nombre!M4) -> 0
A7: FACE À TOI-MÊME | B7: DEEP | C7: =COUNTIF(Questions!C:C,Nombre!A7) -> 76 | H7: AMBITIONS | M7: Admirateur | N7: =COUNTIF(Questions!D:D,Nombre!M5) -> 2
A8: LES DOSSIERS | B8: FUN | C8: =COUNTIF(Questions!C:C,Nombre!A8) -> 52 | H8: AVENIR : | M8: Ambiance | N8: =COUNTIF(Questions!D:D,Nombre!M6) -> 2
A9: PASSIONS & ACTIVITES | B9: ICEBREAKERS | C9: =COUNTIF(Questions!C:C,Nombre!A9) -> 76 | M9: Amis perdus | N9: =COUNTIF(Questions!D:D,Nombre!M7) -> 2
A10: QUI ES-TU ? | B10: ICEBREAKERS | C10: =COUNTIF(Questions!C:C,Nombre!A10) -> 34 | M10: Amitié Durable | N10: =COUNTIF(Questions!D:D,Nombre!M8) -> 2
A11: QUOTIDIEN | B11: ICEBREAKERS | C11: =COUNTIF(Questions!C:C,Nombre!A11) -> 80 | M11: Amitié proche | N11: =COUNTIF(Questions!D:D,Nombre!M9) -> 2
A12: RETOUR EN ARRIERE | B12: DEEP | C12: =COUNTIF(Questions!C:C,Nombre!A12) -> 40 | M12: Amour propre | N12: =COUNTIF(Questions!D:D,Nombre!M10) -> 2
A13: VOYAGES & SORTIE | B13: ICEBREAKERS | C13: =COUNTIF(Questions!C:C,Nombre!A13) -> 40 | M13: Animal | N13: =COUNTIF(Questions!D:D,Nombre!M11) -> 2
A14: EMOTIONS & BIEN-ÊTRE | B14: DEEP | C14: =COUNTIF(Questions!C:C,Nombre!A14) -> 56 | M14: Animal de Compagnie | N14: =COUNTIF(Questions!D:D,Nombre!M12) -> 2
A15: MISE EN SITUATION | B15: ICEBREAKERS | C15: =COUNTIF(Questions!C:C,Nombre!A15) -> 20 | M15: Animation | N15: =COUNTIF(Questions!D:D,Nombre!M13) -> 2
A16: MES OPINIONS | B16: FUN | C16: =COUNTIF(Questions!C:C,Nombre!A16) -> 22 | M16: Anniversaire | N16: =COUNTIF(Questions!D:D,Nombre!M14) -> 2
C17: =COUNTIF(Questions!A2:A647,"") -> 0 | M17: Apparences trompeuses | N17: =COUNTIF(Questions!D:D,Nombre!M15) -> 2
C18: =SUM(C2:C17) -> 678 | M18: Architecture | N18: =COUNTIF(Questions!D:D,Nombre!M16) -> 2
M19: Art | N19: =COUNTIF(Questions!D:D,Nombre!M17) -> 2
M20: Aspirations profondes | N20: =COUNTIF(Questions!D:D,Nombre!M18) -> 2
M21: Astrologie | N21: =COUNTIF(Questions!D:D,Nombre!M19) -> 2
M22: Attentes | N22: =COUNTIF(Questions!D:D,Nombre!M20) -> 2
M23: Au dodo | N23: =COUNTIF(Questions!D:D,Nombre!M21) -> 2
M24: Au travail | N24: =COUNTIF(Questions!D:D,Nombre!M22) -> 2
M25: Autobiographie | N25: =COUNTIF(Questions!D:D,Nombre!M23) -> 2
M26: Avenir | N26: =COUNTIF(Questions!D:D,Nombre!M24) -> 2
M27: Aveux | N27: =COUNTIF(Questions!D:D,Nombre!M25) -> 2
M28: Blague | N28: =COUNTIF(Questions!D:D,Nombre!M27) -> 2
M29: Bodycount | N29: =COUNTIF(Questions!D:D,Nombre!M28) -> 2
M30: Boisson | N30: =COUNTIF(Questions!D:D,Nombre!M29) -> 2
M31: Bon délire | N31: =COUNTIF(Questions!D:D,Nombre!M30) -> 2
M32: Bruit | N32: =COUNTIF(Questions!D:D,Nombre!M31) -> 2
M33: Ca ME SOULE | N33: =COUNTIF(Questions!D:D,Nombre!M32) -> 2
M34: Cadeaux | N34: =COUNTIF(Questions!D:D,Nombre!M33) -> 0
M35: Cadeaux Reçus | N35: =COUNTIF(Questions!D:D,Nombre!M34) -> 2
M36: Célébrité | N36: =COUNTIF(Questions!D:D,Nombre!M35) -> 2
M37: Cette année | N37: =COUNTIF(Questions!D:D,Nombre!M36) -> 2
M38: Chance et malchance | N38: =COUNTIF(Questions!D:D,Nombre!M37) -> 2
M39: Changements | N39: =COUNTIF(Questions!D:D,Nombre!M38) -> 2
... M77: Destination | N77: =COUNTIF(Questions!D:D,Nombre!M76) -> 0
M78: Développement Perso | N78: =COUNTIF(Questions!D:D,Nombre!M78) -> 2
M79: Développements | N79: =COUNTIF(Questions!D:D,Nombre!M79) -> 2
M80: Discussions Idéales | N80: =COUNTIF(Questions!D:D,Nombre!M80) -> 2
M81: Discussions profondes | N81: =COUNTIF(Questions!D:D,Nombre!M77) -> 2
M82: Disney | N82: =COUNTIF(Questions!D:D,Nombre!M81) -> 2
M83: Disputes | N83: =COUNTIF(Questions!D:D,Nombre!M82) -> 2
M84: Drague | N84: =COUNTIF(Questions!D:D,Nombre!M84) -> 2
M85: Economies | N85: =COUNTIF(Questions!D:D,Nombre!M88) -> 2
M86: Écrans | N86: =COUNTIF(Questions!D:D,Nombre!M89) -> 2
M87: Écriture | N87: =COUNTIF(Questions!D:D,Nombre!M90) -> 2
M88: Embrouille | N88: =COUNTIF(Questions!D:D,Nombre!M91) -> 0
M89: En crise | N89: =COUNTIF(Questions!D:D,Nombre!M92) -> 2
M90: Endroits spécifiques | N90: =COUNTIF(Questions!D:D,Nombre!M93) -> 2
M91: Energie | N91: =COUNTIF(Questions!D:D,Nombre!M94) -> 2
M92: Énergie | N92: =COUNTIF(Questions!D:D,Nombre!M95) -> 2
M93: Enfance | N93: =COUNTIF(Questions!D:D,Nombre!M96) -> 2
M94: Engagement | N94: =COUNTIF(Questions!D:D,Nombre!M97) -> 2
M95: Enseignement | N95: =COUNTIF(Questions!D:D,Nombre!M98) -> 2
M96: Etudes | N96: =COUNTIF(Questions!D:D,Nombre!M87) -> 0
M97: Exagérations | N97: =COUNTIF(Questions!D:D,Nombre!M99) -> 2
M98: Expatriations | N98: =COUNTIF(Questions!D:D,Nombre!M100) -> 2
M99: Expériences de voyages | N99: =COUNTIF(Questions!D:D,Nombre!M101) -> 2
M100: Expériences Fondatrices | N100: =COUNTIF(Questions!D:D,Nombre!M102) -> 2
M101: Fail | N101: =COUNTIF(Questions!D:D,Nombre!M103) -> 2
M102: Famille | N102: =COUNTIF(Questions!D:D,Nombre!M104) -> 2
M103: Famille proche | N103: =COUNTIF(Questions!D:D,Nombre!M105) -> 2
M104: Famille secrète | N104: =COUNTIF(Questions!D:D,Nombre!M106) -> 2
M105: Fantasmes | N105: =COUNTIF(Questions!D:D,Nombre!M107) -> 2
M106: Fatigue | N106: =COUNTIF(Questions!D:D,Nombre!M108) -> 2
M107: Fête | N107: =COUNTIF(Questions!D:D,Nombre!M109) -> 2
M108: Fiction | N108: =COUNTIF(Questions!D:D,Nombre!M110) -> 0
... M261: Santé | N261: =COUNTIF(Questions!D:D,Nombre!M263) -> 2
M262: Santé mentale | N262: =COUNTIF(Questions!D:D,Nombre!M26) -> 2
M263: Scènes de films | N263: =COUNTIF(Questions!D:D,Nombre!M264) -> 2
M264: Secret du Groupe | N264: =COUNTIF(Questions!D:D,Nombre!M265) -> 0
M265: Série | N265: =COUNTIF(Questions!D:D,Nombre!M266) -> 2
M266: Sérieux ? | N266: =COUNTIF(Questions!D:D,Nombre!M267) -> 2
M267: Silences & Émotions | N267: =COUNTIF(Questions!D:D,Nombre!M268) -> 2
M268: Situations délicates | N268: =COUNTIF(Questions!D:D,Nombre!M269) -> 2
M269: Social | N269: =COUNTIF(Questions!D:D,Nombre!M270) -> 0
M270: Social | N270: =COUNTIF(Questions!D:D,Nombre!M271) -> 2
M271: Soirée | N271: =COUNTIF(Questions!D:D,Nombre!M272) -> 2
M272: Solitude | N272: =COUNTIF(Questions!D:D,Nombre!M273) -> 0
M273: Solitude | N273: =COUNTIF(Questions!D:D,Nombre!M274) -> 0
M274: Souvenir | N274: =COUNTIF(Questions!D:D,Nombre!M275) -> 2
... M295: Tes Passions | N295: =COUNTIF(Questions!D:D,Nombre!M296) -> 0
M296: Tombé | N296: =COUNTIF(Questions!D:D,Nombre!M83) -> 2
M297: Ton Look & Beauté | N297: =COUNTIF(Questions!D:D,Nombre!M297) -> 2
M298: Traditions Familiales | N298: =COUNTIF(Questions!D:D,Nombre!M298) -> 2
M299: Trajectoire de vie | N299: =COUNTIF(Questions!D:D,Nombre!M299) -> 2
M300: Transport | N300: =COUNTIF(Questions!D:D,Nombre!M300) -> 0
M301: Transports | N301: =COUNTIF(Questions!D:D,Nombre!M301) -> 2
M302: Trivia | N302: =COUNTIF(Questions!D:D,Nombre!M302) -> 2
M303: Trouvé | N303: =COUNTIF(Questions!D:D,Nombre!M303) -> 0
M304: TV | N304: =COUNTIF(Questions!D:D,Nombre!M304) -> 2
M305: Type de films | N305: =COUNTIF(Questions!D:D,Nombre!M305) -> 2
M306: Vacances | N306: =COUNTIF(Questions!D:D,Nombre!M306) -> 2
M307: Vériés | N307: =COUNTIF(Questions!D:D,Nombre!M307) -> 0
M308: Vérités | N308: =COUNTIF(Questions!D:D,Nombre!M308) -> 2
... M313: What | N313: =COUNTIF(Questions!D:D,Nombre!M313) -> 2

Sheet Noms Themes
A1: AMBITIONS 🚀 | B1: AMBITIONS
A2: Tes rêves, ton argent, ta vision ! Que veux-tu vraiment construire ? | B2: Your dreams, your money, your vision. What are you actually building?
A3: →
A4: AMIS & FAMILLE 🫂 | B4: FAMILY & FRIENDS
A5: Des questions sur tes liens avec ceux qui comptent vraiment ! | B5: Questions about the people who matter most. No sugarcoating.
A6: →
A7: HOT 🔞 | B7: SPICYYY
A8: En dehors des regards ! Pour les adultes uniquement. | B8: Adults only. No audience, no filter, no limits.
A9: →
A10: CINÉ & MUSIQUE 🎬 | B10: MOVIES & MUSIC
A11: Ce que tu écoutes, ce que tu regardes, ce que ça dit de toi sans que tu t'en rendes compte ! | B11: What you watch, what you listen to, and what it says about you without you realizing it !
A12: →
A13: ENTRE NOUS 👀 | B13: BETWEEN US
A14: Des questions sur la dynamique de groupe elle-même ! | B14: Questions about the group itself. Let's get into it.
A15: →
A16: FACE À TOI-MÊME 🪞 | B16: IN THE MIRROR
A17: Pas de filtre : ce que tu sais de toi mais que tu dis rarement. | B17: No filter. The things you know about yourself but rarely say out loud.
A18: →
A19: LES DOSSIERS 📂 | B19: THE RECEIPTS
A20: Opinions tranchées, aveux gênants, Onskoné ou Onvastapé ! | B20: Sharp opinions, awkward confessions. We see you.
A21: →
A22: PASSIONS & ACTIVITÉS 🎯 | B22: HOBBIES & PASSIONS
A23: Ce qui te fait vibrer dans la vie ! | B23: The things that actually make you come alive.
A24: →
A25: QUI ES-TU ? 🧬 | B25: ABOUT YOU
A26: Ton introduction, et les premiers détails qui apprennent à savoir qui tu es ! | B26: Your intro. The first details that tell us who you really are.
A27: →
A28: QUOTIDIEN ☀️ | B28: DAILY LIFE
A29: Le matin, les habitudes, les petits riens ! | B29: Mornings, habits, routines. The small stuff that's actually everything.
A30: →
A31: RETOUR EN ARRIÈRE ⏪ | B31: BACK IN THE DAY
A32: L'enfance, les regrets, les tournants. Tout ce qui t'a construit ! | B32: Childhood, regrets, turning points. Everything that made you who you are.
A33: →
A34: VOYAGES & SORTIE 🌍 | B34: PARTIES & TRAVEL
A35: Où tu vas et où tu sors ! | B35: Where you travel, and what you get up to !
A36: →
A37: ÉMOTIONS & BIEN-ÊTRE 💛 | B37: FEELINGS
A38: Ce que tu ressens vraiment ! Petite introspection. | B38: What you're actually feeling. A little introspection goes a long way.
A39: →
A40: MISE EN SITUATION 🎭 | B40: WYD?
A41: On te met dans un contexte, et on juge ce que ça donne ! | B41: What would you do ? We put you in a scenario, show us how you act
A42: →
A43: TES OPINIONS 🗣️ | B43: HOT TAKES
A44: Ce que tu penses à voix haute, sur plusieurs sujets... particuliers ! | B44: Your opinions, out loud, on everything, on some … subjects.

Sheet 📊 Résumé
A1: Thème | B1: Nb Questions | C1: Nb Types
A2: AMBITIONS | B2: 44 | C2: 23
A3: AMIS & FAMILLE | B3: 30 | C3: 17
A4: AMOUR & SÉDUCTION | B4: 27 | C4: 14
A5: CINÉ & SÉRIES | B5: 27 | C5: 14
A6: ENTRE NOUS | B6: 33 | C6: 17
A7: FACE À TOI-MÊME | B7: 113 | C7: 57
A8: HUMOUR & DOSSIERS | B8: 47 | C8: 24
A9: LE MONDE | B9: 22 | C9: 11
A10: MUSIQUE | B10: 18 | C10: 10
A11: PASSIONS & CRÉA | B11: 98 | C11: 49
A12: QUI ES-TU ? | B12: 49 | C12: 26
A13: QUOTIDIEN | B13: 94 | C13: 49
... A17: TOTAL | B17: 705 | C17: 364
